[
  {
    "startup_profile_id": 1,
    "user_id": 1,
    "company_name": null,
    "industry_id": null,
    "funding_stage_id": null,
    "elevator_pitch": null,
    "strengths": null,
    "weaknesses": null,
    "opportunities": null,
    "threats": null,
    "funding_goal": null,
    "currency": "USD",
    "website": null,
    "founded_year": null,
    "team_size": null,
    "location": null,
    "created_at": "2025-11-10T16:19:13.976Z"
  },
  {
    "startup_profile_id": 2,
    "user_id": 3,
    "company_name": "FAST NUCES Islamabad",
    "industry_id": 5,
    "funding_stage_id": 1,
    "elevator_pitch": "sup",
    "strengths": "programming",
    "weaknesses": "talking",
    "opportunities": "none",
    "threats": "atom bomb",
    "funding_goal": 2000000,
    "currency": "USD",
    "website": "https://github.com/UsmanPrime",
    "founded_year": 2005,
    "team_size": 10,
    "location": "islamabad.pakistan",
    "created_at": "2025-11-10T16:20:02.578Z",
    "updated_at": "2025-11-15T12:15:05.800Z"
  },
  {
    "startup_profile_id": 3,
    "user_id": 5,
    "company_name": null,
    "industry_id": null,
    "funding_stage_id": null,
    "elevator_pitch": null,
    "strengths": null,
    "weaknesses": null,
    "opportunities": null,
    "threats": null,
    "funding_goal": null,
    "currency": "USD",
    "website": null,
    "founded_year": null,
    "team_size": null,
    "location": null,
    "created_at": "2025-11-10T19:08:47.591Z"
  },
  {
    "startup_profile_id": 4,
    "user_id": 6,
    "company_name": "BrightTech Solutions",
    "location": " San Francisco, USA",
    "industry_id": 1,
    "funding_stage_id": 2,
    "target_funding_amount": null,
    "problem_statement": null,
    "solution_overview": null,
    "business_model": null,
    "market_size": null,
    "traction": null,
    "team_size": 8,
    "website_url": null,
    "pitch_deck_url": null,
    "created_at": "2025-11-15T15:55:56.290Z",
    "elevator_pitch": "BrightTech Solutions develops AI-powered tools to simplify business operations and improve productivity for SMEs.",
    "strengths": "Innovative AI algorithms, strong founding team, agile development process",
    "weaknesses": "Limited marketing budget, small initial user base",
    "opportunities": "Growing demand for automation, potential partnerships with enterprise clients",
    "threats": "Competition from established SaaS providers, rapidly changing technology",
    "funding_goal": 500000,
    "currency": "USD",
    "website": "https://brighttech.com",
    "founded_year": 2023,
    "updated_at": "2025-11-15T16:00:51.028Z"
  },
  {
    "startup_profile_id": 5,
    "user_id": 8,
    "company_name": null,
    "location": null,
    "industry_id": null,
    "funding_stage_id": null,
    "target_funding_amount": null,
    "problem_statement": null,
    "solution_overview": null,
    "business_model": null,
    "market_size": null,
    "traction": null,
    "team_size": null,
    "website_url": null,
    "pitch_deck_url": null,
    "created_at": "2025-11-15T18:04:12.018Z"
  },
  {
    "startup_profile_id": 6,
    "user_id": 9,
    "company_name": null,
    "location": null,
    "industry_id": null,
    "funding_stage_id": null,
    "target_funding_amount": null,
    "problem_statement": null,
    "solution_overview": null,
    "business_model": null,
    "market_size": null,
    "traction": null,
    "team_size": null,
    "website_url": null,
    "pitch_deck_url": null,
    "created_at": "2025-11-15T18:18:12.912Z"
  },
  {
    "startup_profile_id": 7,
    "user_id": 10,
    "company_name": null,
    "location": null,
    "industry_id": null,
    "funding_stage_id": null,
    "target_funding_amount": null,
    "problem_statement": null,
    "solution_overview": null,
    "business_model": null,
    "market_size": null,
    "traction": null,
    "team_size": null,
    "website_url": null,
    "pitch_deck_url": null,
    "created_at": "2025-11-17T10:09:27.512Z"
  }
]